unique_web_search/__init__.py
unique_web_search/client_settings.py
unique_web_search/config.py
unique_web_search/prompts.py
unique_web_search/schema.py
unique_web_search/service.py
unique_web_search/services/client/proxy_config.py
unique_web_search/services/content_processing/__init__.py
unique_web_search/services/content_processing/config.py
unique_web_search/services/content_processing/service.py
unique_web_search/services/crawlers/README.md
unique_web_search/services/crawlers/__init__.py
unique_web_search/services/crawlers/base.py
unique_web_search/services/crawlers/basic.py
unique_web_search/services/crawlers/crawl4ai.py
unique_web_search/services/crawlers/firecrawl.py
unique_web_search/services/crawlers/jina.py
unique_web_search/services/crawlers/tavily.py
unique_web_search/services/executors/README.md
unique_web_search/services/executors/__init__.py
unique_web_search/services/executors/base_executor.py
unique_web_search/services/executors/configs/__init__.py
unique_web_search/services/executors/configs/base.py
unique_web_search/services/executors/configs/prompts.py
unique_web_search/services/executors/configs/v1_config.py
unique_web_search/services/executors/configs/v2_config.py
unique_web_search/services/executors/web_search_v1_executor.py
unique_web_search/services/executors/web_search_v2_executor.py
unique_web_search/services/helpers.py
unique_web_search/services/search_engine/README.md
unique_web_search/services/search_engine/__init__.py
unique_web_search/services/search_engine/base.py
unique_web_search/services/search_engine/bing.py
unique_web_search/services/search_engine/brave.py
unique_web_search/services/search_engine/custom_api.py
unique_web_search/services/search_engine/firecrawl.py
unique_web_search/services/search_engine/google.py
unique_web_search/services/search_engine/jina.py
unique_web_search/services/search_engine/schema.py
unique_web_search/services/search_engine/tavily.py
unique_web_search/services/search_engine/utils/bing/__init__.py
unique_web_search-1.9.1.dist-info/WHEEL
unique_web_search-1.9.1.dist-info/METADATA
unique_web_search-1.9.1.dist-info/RECORD
