Metadata-Version: 2.3
Name: unique-web-search
Version: 1.9.1
Summary: 
Author: Andreas Hauri, Gustav Hartz, Rami Azouz
Author-email: Andreas Hauri <andreas@unique.ch>, Gustav Hartz <gustav.hartz.ext@unique.ch>, Rami Azouz <rami.ext@unique.ch>
License: Proprietary
Requires-Dist: typing-extensions>=4.14.1,<5
Requires-Dist: pydantic>=2.12.3,<3
Requires-Dist: pydantic-settings>=2.10.1,<3
Requires-Dist: timeout-decorator>=0.5.0,<1
Requires-Dist: markdownify>=0.14.1,<1
Requires-Dist: fake-useragent>=2.2.0,<3
Requires-Dist: crawl4ai>=0.6.3,<1
Requires-Dist: firecrawl>=3.3.2,<4
Requires-Dist: tavily-python>=0.7.11,<1
Requires-Dist: unidecode>=1.4.0,<2
Requires-Dist: azure-ai-projects>=1.0.0,<2
Requires-Dist: azure-identity>=1.25.0,<2
Requires-Dist: unique-toolkit>=1.45.0,<2
Requires-Dist: azure-core>=1.36.0,<2
Requires-Dist: google-cloud-aiplatform>=1.128.0,<2
Requires-Dist: google-auth>=2.43.0,<3
Requires-Dist: google-generativeai>=0.8.5,<0.9
Requires-Dist: langchain-text-splitters>=1.0.0,<2
Requires-Dist: httpx>=0.28.1
Requires-Dist: tiktoken>=0.12.0
Requires-Dist: openai>=1.109.1
Requires-Dist: certifi>=2025.11.12
Requires-Python: >=3.12, <4.0
